{
 "X": [
  {
   "is_class": false,
   "is_explicit": false,
   "module": "numpy",
   "module_short": "numpy",
   "name": "ndarray"
  }
 ],
 "X.shape": [
  {
   "is_class": false,
   "is_explicit": false,
   "module": "builtins",
   "module_short": "builtins",
   "name": "tuple"
  }
 ],
 "Xs": [
  {
   "is_class": false,
   "is_explicit": false,
   "module": "builtins",
   "module_short": "builtins",
   "name": "list"
  }
 ],
 "_": [
  {
   "is_class": false,
   "is_explicit": false,
   "module": "matplotlib.axes._axes",
   "module_short": "matplotlib.axes",
   "name": "Axes"
  },
  {
   "is_class": false,
   "is_explicit": false,
   "module": "matplotlib.axes",
   "module_short": "matplotlib.axes",
   "name": "Axes"
  },
  {
   "is_class": false,
   "is_explicit": false,
   "module": "matplotlib",
   "module_short": "matplotlib",
   "name": "Axes"
  }
 ],
 "ax": [
  {
   "is_class": false,
   "is_explicit": false,
   "module": "matplotlib.axes._axes",
   "module_short": "matplotlib.axes",
   "name": "Axes"
  },
  {
   "is_class": false,
   "is_explicit": false,
   "module": "matplotlib.axes",
   "module_short": "matplotlib.axes",
   "name": "Axes"
  },
  {
   "is_class": false,
   "is_explicit": false,
   "module": "matplotlib",
   "module_short": "matplotlib",
   "name": "Axes"
  }
 ],
 "copy.deepcopy": [
  {
   "is_class": false,
   "is_explicit": false,
   "module": "builtins",
   "module_short": "builtins",
   "name": "function"
  },
  {
   "is_class": false,
   "is_explicit": false,
   "module": "copy",
   "module_short": "copy",
   "name": "deepcopy"
  }
 ],
 "fig": [
  {
   "is_class": false,
   "is_explicit": false,
   "module": "matplotlib.figure",
   "module_short": "matplotlib.figure",
   "name": "Figure"
  },
  {
   "is_class": false,
   "is_explicit": false,
   "module": "matplotlib",
   "module_short": "matplotlib",
   "name": "Figure"
  }
 ],
 "get_summary": [
  {
   "is_class": false,
   "is_explicit": false,
   "module": "builtins",
   "module_short": "builtins",
   "name": "function"
  },
  {
   "is_class": false,
   "is_explicit": false,
   "module": "imml.explore",
   "module_short": "imml.explore",
   "name": "get_summary"
  }
 ],
 "inc_Xs": [
  {
   "is_class": false,
   "is_explicit": false,
   "module": "builtins",
   "module_short": "builtins",
   "name": "list"
  }
 ],
 "make_classification": [
  {
   "is_class": false,
   "is_explicit": false,
   "module": "builtins",
   "module_short": "builtins",
   "name": "function"
  },
  {
   "is_class": false,
   "is_explicit": false,
   "module": "sklearn.datasets",
   "module_short": "sklearn.datasets",
   "name": "make_classification"
  }
 ],
 "np.nan": [
  {
   "is_class": false,
   "is_explicit": false,
   "module": "builtins",
   "module_short": "builtins",
   "name": "float"
  },
  {
   "is_class": false,
   "is_explicit": false,
   "module": "numpy",
   "module_short": "numpy",
   "name": "nan"
  }
 ],
 "pid": [
  {
   "is_class": false,
   "is_explicit": false,
   "module": "builtins",
   "module_short": "builtins",
   "name": "function"
  },
  {
   "is_class": false,
   "is_explicit": false,
   "module": "imml.statistics",
   "module_short": "imml.statistics",
   "name": "pid"
  }
 ],
 "plot_pid": [
  {
   "is_class": false,
   "is_explicit": false,
   "module": "builtins",
   "module_short": "builtins",
   "name": "function"
  },
  {
   "is_class": false,
   "is_explicit": false,
   "module": "imml.visualize",
   "module_short": "imml.visualize",
   "name": "plot_pid"
  }
 ],
 "random_state": [
  {
   "is_class": false,
   "is_explicit": false,
   "module": "builtins",
   "module_short": "builtins",
   "name": "int"
  }
 ],
 "rus": [
  {
   "is_class": false,
   "is_explicit": false,
   "module": "builtins",
   "module_short": "builtins",
   "name": "list"
  }
 ],
 "summary": [
  {
   "is_class": false,
   "is_explicit": false,
   "module": "pandas.core.frame",
   "module_short": "pandas.core.frame",
   "name": "DataFrame"
  },
  {
   "is_class": false,
   "is_explicit": false,
   "module": "pandas.core",
   "module_short": "pandas.core",
   "name": "DataFrame"
  },
  {
   "is_class": false,
   "is_explicit": false,
   "module": "pandas",
   "module_short": "pandas",
   "name": "DataFrame"
  }
 ],
 "summary.columns": [
  {
   "is_class": false,
   "is_explicit": false,
   "module": "pandas.core.indexes.base",
   "module_short": "pandas.core.indexes.base",
   "name": "Index"
  },
  {
   "is_class": false,
   "is_explicit": false,
   "module": "pandas.core.indexes",
   "module_short": "pandas.core.indexes",
   "name": "Index"
  },
  {
   "is_class": false,
   "is_explicit": false,
   "module": "pandas.core",
   "module_short": "pandas.core",
   "name": "Index"
  },
  {
   "is_class": false,
   "is_explicit": false,
   "module": "pandas",
   "module_short": "pandas",
   "name": "Index"
  }
 ],
 "summary.index": [
  {
   "is_class": false,
   "is_explicit": false,
   "module": "pandas.core.indexes.base",
   "module_short": "pandas.core.indexes.base",
   "name": "Index"
  },
  {
   "is_class": false,
   "is_explicit": false,
   "module": "pandas.core.indexes",
   "module_short": "pandas.core.indexes",
   "name": "Index"
  },
  {
   "is_class": false,
   "is_explicit": false,
   "module": "pandas.core",
   "module_short": "pandas.core",
   "name": "Index"
  },
  {
   "is_class": false,
   "is_explicit": false,
   "module": "pandas",
   "module_short": "pandas",
   "name": "Index"
  }
 ],
 "summary.index.str.replace": [
  {
   "is_class": false,
   "is_explicit": false,
   "module": "pandas.core.strings.accessor",
   "module_short": "pandas.core.strings.accessor",
   "name": "StringMethods.replace"
  },
  {
   "is_class": false,
   "is_explicit": false,
   "module": "pandas.core.strings",
   "module_short": "pandas.core.strings",
   "name": "StringMethods.replace"
  },
  {
   "is_class": false,
   "is_explicit": false,
   "module": "pandas.core",
   "module_short": "pandas.core",
   "name": "StringMethods.replace"
  },
  {
   "is_class": false,
   "is_explicit": false,
   "module": "pandas",
   "module_short": "pandas",
   "name": "StringMethods.replace"
  },
  {
   "is_class": false,
   "is_explicit": false,
   "module": "pandas.core.base",
   "module_short": "pandas.core.base",
   "name": "NoNewAttributesMixin.replace"
  },
  {
   "is_class": false,
   "is_explicit": false,
   "module": "pandas.core",
   "module_short": "pandas.core",
   "name": "NoNewAttributesMixin.replace"
  },
  {
   "is_class": false,
   "is_explicit": false,
   "module": "pandas",
   "module_short": "pandas",
   "name": "NoNewAttributesMixin.replace"
  }
 ],
 "y": [
  {
   "is_class": false,
   "is_explicit": false,
   "module": "numpy",
   "module_short": "numpy",
   "name": "ndarray"
  }
 ]
}